fast_qrs_detector/__init__.py
fast_qrs_detector/fast_qrs_detector.py
fast_qrs_detector/print_qrs.py
fast_qrs_detector-0.1.2.dist-info/licenses/LICENSE
fast_qrs_detector-0.1.2.dist-info/METADATA
fast_qrs_detector-0.1.2.dist-info/WHEEL
fast_qrs_detector-0.1.2.dist-info/top_level.txt
fast_qrs_detector-0.1.2.dist-info/RECORD
