Metadata-Version: 2.4
Name: fast-qrs-detector
Version: 0.1.2
Summary: Package for detecting QRS in a ECG signal.
Author-email: Fournier Jean-Charles <jean-charles.fournier@hotmail.com>
License: Eclipse Public License - v 2.0
Project-URL: homepage, https://www.aura.healthcare
Project-URL: repository, https://github.com/Genialmanos/QRS_Detector
Requires-Python: >=3.6
License-File: LICENSE
Dynamic: license-file
